converter_package_Bajiio/__init__.py
converter_package_Bajiio/converter.py
converter_package_bajiio-0.0.1.dist-info/METADATA
converter_package_bajiio-0.0.1.dist-info/WHEEL
converter_package_bajiio-0.0.1.dist-info/licenses/LICENSE
converter_package_bajiio-0.0.1.dist-info/RECORD
