Metadata-Version: 2.1
Name: converter_package_Bajiio
Version: 0.0.1
Summary: A small example package
Project-URL: Homepage, https://github.com/Bajiio/tp2_git/
Project-URL: Bug Tracker, https://github.com/Bajiio/tp2_git/issues
Author-email: Mathias <mathias@example.com>
License-File: LICENSE
Classifier: License :: OSI Approved :: MIT License
Classifier: Operating System :: OS Independent
Classifier: Programming Language :: Python :: 3
Requires-Python: >=3.7
